opensearch_demos_utils/__init__.py
opensearch_demos_utils/colab_installer.py
opensearch_demos_utils/config_templates.py
opensearch_demos_utils/connection.py
opensearch_demos_utils/data_loader.py
opensearch_demos_utils/sample_datasets.py
opensearch_demos_utils/visualization.py
opensearch_demos_utils-1.0.0.dist-info/licenses/LICENSE
opensearch_demos_utils-1.0.0.dist-info/METADATA
opensearch_demos_utils-1.0.0.dist-info/WHEEL
opensearch_demos_utils-1.0.0.dist-info/top_level.txt
opensearch_demos_utils-1.0.0.dist-info/RECORD
