Metadata-Version: 2.4
Name: opensearch-demos-utils
Version: 1.0.0
Summary: Utilities for OpenSearch demonstrations and educational content
Home-page: https://github.com/opensearch-project/opensearch-demos
Author: OpenSearch Demos Team
Author-email: OpenSearch Demos Team <support@example.com>
Maintainer-email: OpenSearch Demos Team <support@example.com>
License-Expression: Apache-2.0
Project-URL: Homepage, https://github.com/opensearch-project/opensearch-demos
Project-URL: Documentation, https://github.com/opensearch-project/opensearch-demos/blob/main/README.md
Project-URL: Repository, https://github.com/opensearch-project/opensearch-demos
Project-URL: Bug Reports, https://github.com/opensearch-project/opensearch-demos/issues
Project-URL: Changelog, https://github.com/opensearch-project/opensearch-demos/blob/main/CHANGELOG.md
Keywords: opensearch,elasticsearch,search,analytics,demos,education,colab,jupyter,astra,datastax
Classifier: Development Status :: 4 - Beta
Classifier: Intended Audience :: Developers
Classifier: Intended Audience :: Education
Classifier: Operating System :: OS Independent
Classifier: Programming Language :: Python :: 3
Classifier: Programming Language :: Python :: 3.8
Classifier: Programming Language :: Python :: 3.9
Classifier: Programming Language :: Python :: 3.10
Classifier: Programming Language :: Python :: 3.11
Classifier: Programming Language :: Python :: 3.12
Classifier: Topic :: Database :: Database Engines/Servers
Classifier: Topic :: Education
Classifier: Topic :: Software Development :: Libraries :: Python Modules
Classifier: Topic :: Text Processing :: Indexing
Requires-Python: >=3.8
License-File: LICENSE
Requires-Dist: opensearch-py<3.0.0,>=2.4.0
Requires-Dist: pandas<3.0.0,>=1.3.0
Requires-Dist: matplotlib<4.0.0,>=3.5.0
Requires-Dist: seaborn<1.0.0,>=0.11.0
Requires-Dist: numpy<2.0.0,>=1.21.0
Requires-Dist: requests<3.0.0,>=2.25.0
Provides-Extra: dev
Requires-Dist: pytest<8.0.0,>=7.0.0; extra == "dev"
Requires-Dist: pytest-cov<5.0.0,>=4.0.0; extra == "dev"
Requires-Dist: black<24.0.0,>=22.0.0; extra == "dev"
Requires-Dist: flake8<7.0.0,>=4.0.0; extra == "dev"
Requires-Dist: mypy<2.0.0,>=0.950; extra == "dev"
Requires-Dist: build<1.0.0,>=0.8.0; extra == "dev"
Requires-Dist: twine<5.0.0,>=4.0.0; extra == "dev"
Requires-Dist: wheel<1.0.0,>=0.37.0; extra == "dev"
Provides-Extra: notebook
Requires-Dist: jupyter<2.0.0,>=1.0.0; extra == "notebook"
Requires-Dist: ipywidgets<9.0.0,>=7.6.0; extra == "notebook"
Requires-Dist: nbformat<6.0.0,>=5.4.0; extra == "notebook"
Requires-Dist: nbconvert<8.0.0,>=6.5.0; extra == "notebook"
Provides-Extra: colab
Requires-Dist: ipywidgets<9.0.0,>=7.6.0; extra == "colab"
Dynamic: author
Dynamic: home-page
Dynamic: license-file
Dynamic: requires-python
